fastai2/__init__.py
fastai2/_nbdev.py
fastai2/_pytorch_doc.py
fastai2/basics.py
fastai2/collab.py
fastai2/distributed.py
fastai2/fp16_utils.py
fastai2/imports.py
fastai2/interpret.py
fastai2/launch.py
fastai2/layers.py
fastai2/learner.py
fastai2/metrics.py
fastai2/optimizer.py
fastai2/test_utils.py
fastai2/torch_basics.py
fastai2/torch_core.py
fastai2/torch_imports.py
fastai2/callback/__init__.py
fastai2/callback/all.py
fastai2/callback/captum.py
fastai2/callback/core.py
fastai2/callback/cutmix.py
fastai2/callback/data.py
fastai2/callback/fp16.py
fastai2/callback/hook.py
fastai2/callback/mixup.py
fastai2/callback/neptune.py
fastai2/callback/progress.py
fastai2/callback/rnn.py
fastai2/callback/schedule.py
fastai2/callback/tensorboard.py
fastai2/callback/tracker.py
fastai2/callback/training.py
fastai2/callback/wandb.py
fastai2/data/__init__.py
fastai2/data/all.py
fastai2/data/block.py
fastai2/data/checks.txt
fastai2/data/core.py
fastai2/data/external.py
fastai2/data/load.py
fastai2/data/transforms.py
fastai2/medical/__init__.py
fastai2/medical/imaging.py
fastai2/medical/text.py
fastai2/tabular/__init__.py
fastai2/tabular/all.py
fastai2/tabular/core.py
fastai2/tabular/data.py
fastai2/tabular/learner.py
fastai2/tabular/model.py
fastai2/text/__init__.py
fastai2/text/all.py
fastai2/text/core.py
fastai2/text/data.py
fastai2/text/learner.py
fastai2/text/models/__init__.py
fastai2/text/models/awdlstm.py
fastai2/text/models/bwd_forget_mult_cuda.cpp
fastai2/text/models/bwd_forget_mult_cuda_kernel.cu
fastai2/text/models/core.py
fastai2/text/models/forget_mult_cuda.cpp
fastai2/text/models/forget_mult_cuda_kernel.cu
fastai2/text/models/qrnn.py
fastai2/vision/__init__.py
fastai2/vision/all.py
fastai2/vision/augment.py
fastai2/vision/core.py
fastai2/vision/data.py
fastai2/vision/gan.py
fastai2/vision/learner.py
fastai2/vision/utils.py
fastai2/vision/widgets.py
fastai2/vision/models/__init__.py
fastai2/vision/models/all.py
fastai2/vision/models/unet.py
fastai2-0.0.30.dist-info/LICENSE
fastai2-0.0.30.dist-info/METADATA
fastai2-0.0.30.dist-info/WHEEL
fastai2-0.0.30.dist-info/top_level.txt
fastai2-0.0.30.dist-info/RECORD
