Metadata-Version: 2.1
Name: fastai2
Version: 0.0.30
Summary: Version 2 of the fastai library
Home-page: https://github.com/fastai/fastai2
Author: Jeremy Howard, Sylvain Gugger, and contributors
Author-email: info@fast.ai
License: Apache Software License 2.0
Keywords: fastai,deep learning,machine learning
Platform: UNKNOWN
Classifier: Development Status :: 2 - Pre-Alpha
Classifier: Intended Audience :: Developers
Classifier: License :: OSI Approved :: Apache Software License
Classifier: Natural Language :: English
Classifier: Programming Language :: Python :: 3.6
Classifier: Programming Language :: Python :: 3.7
Classifier: Programming Language :: Python :: 3.8
Requires-Python: >=3.6
Requires-Dist: pip
Requires-Dist: packaging
Requires-Dist: fastcore (>=0.1.34)
Requires-Dist: torchvision (>=0.7)
Requires-Dist: matplotlib
Requires-Dist: pandas
Requires-Dist: requests
Requires-Dist: pyyaml
Requires-Dist: fastprogress (>=0.2.4)
Requires-Dist: pillow
Requires-Dist: scikit-learn
Requires-Dist: scipy
Requires-Dist: spacy
Requires-Dist: torch (>=1.6.0)
Provides-Extra: dev
Requires-Dist: nbdev (>=0.2.20) ; extra == 'dev'
